package_vehicules/__init__.py
package_vehicules/plane.py
package_vehicules/land/__init__.py
package_vehicules/land/green.py
package_vehicules/land/motor.py
package_vehicules/sea/__init__.py
package_vehicules/sea/motor.py
package_vehicules/sea/sail.py
package_vehicules-1.0.0.data/data/vehicule_speed/speed.dat
package_vehicules-1.0.0.dist-info/METADATA
package_vehicules-1.0.0.dist-info/WHEEL
package_vehicules-1.0.0.dist-info/entry_points.txt
package_vehicules-1.0.0.dist-info/top_level.txt
package_vehicules-1.0.0.dist-info/RECORD
